README.md
setup.py
run_octave/__init__.py
run_octave/run_octave.py
run_octave.egg-info/PKG-INFO
run_octave.egg-info/SOURCES.txt
run_octave.egg-info/dependency_links.txt
run_octave.egg-info/requires.txt
run_octave.egg-info/top_level.txt