Metadata-Version: 2.1
Name: run-octave
Version: 1.0.1
Summary: A package to run Octave functions and scripts in the Python interpreter!
Home-page: https://github.com/ferreirad08/run-octave
Author: David Ferreira
Author-email: ferreirad08@gmail.com
License: MIT
Platform: UNKNOWN
Classifier: Programming Language :: Python :: 3
Classifier: License :: OSI Approved :: MIT License
Classifier: Operating System :: OS Independent
Requires-Python: >=3.8.6
